holopatcher/__init__.py
holopatcher/__main__.py
holopatcher/app.py
holopatcher/cli.py
holopatcher/config.py
holopatcher/core.py
holopatcher-2.0.0a3.dist-info/LICENSE.txt
holopatcher-2.0.0a3.dist-info/METADATA
holopatcher-2.0.0a3.dist-info/WHEEL
holopatcher-2.0.0a3.dist-info/entry_points.txt
holopatcher-2.0.0a3.dist-info/top_level.txt
holopatcher-2.0.0a3.dist-info/RECORD
