Metadata-Version: 2.1
Name: holopatcher
Version: 2.0.0a3
Summary: A faster, cross-platform alternative to TSLPatcher written in Python.
Author: NickHugi
Maintainer-email: th3w1zard1 <halomastar@gmail.com>
License: LGPL-3.0-or-later
Project-URL: Homepage, https://deadlystream.com/files/file/2243-holopatcher/
Project-URL: Documentation, https://github.com/OldRepublicDevs/PyKotor/wiki/Installing-Mods-with-HoloPatcher
Project-URL: Repository, https://github.com/OldRepublicDevs/PyKotor.git
Project-URL: Issues, https://github.com/OldRepublicDevs/PyKotor/issues
Project-URL: Changelog, https://github.com/OldRepublicDevs/PyKotor/releases
Keywords: kotor,kotor1,kotor2,tsl,star-wars,knights-of-the-old-republic,modding,patcher,installer,tslpatcher,holopatcher,pykotor
Classifier: Development Status :: 5 - Production/Stable
Classifier: Intended Audience :: End Users/Desktop
Classifier: Intended Audience :: Developers
Classifier: License :: OSI Approved :: GNU Lesser General Public License v3 or later (LGPLv3+)
Classifier: Operating System :: OS Independent
Classifier: Programming Language :: Python :: 3
Classifier: Programming Language :: Python :: 3.8
Classifier: Programming Language :: Python :: 3.9
Classifier: Programming Language :: Python :: 3.10
Classifier: Programming Language :: Python :: 3.11
Classifier: Programming Language :: Python :: 3.12
Classifier: Topic :: Games/Entertainment
Classifier: Topic :: Games/Entertainment :: Role-Playing
Classifier: Topic :: System :: Software Distribution
Classifier: Environment :: Console
Classifier: Environment :: X11 Applications :: Qt
Requires-Python: >=3.8
License-File: LICENSE.txt
Requires-Dist: pykotor>=2.0.2
Requires-Dist: charset-normalizer<3.4,>=2.0
Requires-Dist: pycryptodome
Requires-Dist: requests<2.32.0,>=2.25.0; python_version < "3.9"
Requires-Dist: requests>=2.25.0; python_version >= "3.9"
Provides-Extra: dev
Requires-Dist: pytest>=7.0.0; extra == "dev"
Requires-Dist: ruff>=0.1.0; extra == "dev"
Provides-Extra: gui
Requires-Dist: PyQt5>=5.15; platform_python_implementation == "CPython" and extra == "gui"
Requires-Dist: PySide6; platform_python_implementation == "PyPy" and extra == "gui"
Provides-Extra: rtf
Requires-Dist: pypandoc; extra == "rtf"
Requires-Dist: PyWebView; extra == "rtf"
Provides-Extra: updates
Requires-Dist: requests; extra == "updates"
Requires-Dist: pycryptodome; extra == "updates"
